{
    "teamCountTotal": 2900,
    "pageTotal": 45,
    "pageCurrent": 18,
    "teamCountPage": 65,
    "teams": [
        {
            "website": null,
            "city": "Marietta ",
            "nameFull": "GE Volunteers / Taylor & Mathis / United Technologies-Automated Logic / Novelis / Women in Technology / Cobb EMC / Lockheed Martin / Randstad & WALTON HIGH SCHOOL",
            "stateProv": "Georgia",
            "nameShort": "Walton Robotics",
            "country": "USA",
            "districtCode": null,
            "rookieYear": 2009,
            "robotName": "Ralph",
            "teamNumber": 2974
        },
        {
            "website": null,
            "city": "Sammamish",
            "nameFull": "The Boeing Company/Issaquah Schools Foundation & SKYLINE HIGH SCHOOL",
            "stateProv": "Washington",
            "nameShort": "Spartabots",
            "country": "USA",
            "districtCode": "PNW",
            "rookieYear": 2009,
            "robotName": "TBD",
            "teamNumber": 2976
        },
        {
            "website": null,
            "city": "La Crescent",
            "nameFull": "La Crescent Booster Club/Ace Communications Group/Mathy Construction & LACRESCENT SENIOR HIGH & Seven Rivers Robotics Coalition",
            "stateProv": "Minnesota",
            "nameShort": "Sir Lancer Bots",
            "country": "USA",
            "districtCode": null,
            "rookieYear": 2009,
            "robotName": "Sasha",
            "teamNumber": 2977
        },
        {
            "website": null,
            "city": "St. Louis",
            "nameFull": "The Boeing Company / The Doerr Family / HTE Technologies / Joseph Deasy / Optimist Club of Clayton / SIGN-A-RAMA / Vinci LLC / Century Fire Sprinklers, Inc / Drass Fabrication & Design   / Dan Zoernig Illustrations & BISHOP DU BOURG HIGH SCHOOL",
            "stateProv": "Missouri",
            "nameShort": "Cavaliers",
            "country": "USA",
            "districtCode": null,
            "rookieYear": 2009,
            "robotName": "Calypso",
            "teamNumber": 2978
        },
        {
            "website": null,
            "city": "Oak Harbor",
            "nameFull": "The Boeing Company / United Technologies / NASA / Oak Harbor Educational Foundation / Office of the Superintendent of Public Instruction / North Whidbey Lions Club / Oak Harbor Lions Club / Soroptimist International of Oak Harbor / Oak Harbor Rotary Club / Ashley's Design / Krieg Construction / Bowman Manufacturing / Trossen Robotics & OAK HARBOR HIGH SCHOOL",
            "stateProv": "Washington",
            "nameShort": "The Whidbey Island Wild Cats",
            "country": "USA",
            "districtCode": "PNW",
            "rookieYear": 2009,
            "robotName": "\"Beetle\"",
            "teamNumber": 2980
        },
        {
            "website": null,
            "city": "La Jolla",
            "nameFull": "Dini Group/Qualcomm & LA JOLLA HIGH",
            "stateProv": "California",
            "nameShort": "The Vikings",
            "country": "USA",
            "districtCode": null,
            "rookieYear": 2009,
            "robotName": "Fat Yao",
            "teamNumber": 2984
        },
        {
            "website": null,
            "city": "Oklahoma City",
            "nameFull": "Oklahoma State Department of Education/NASA/Mr. and Mrs. Allen Pease/ITT Technical Institute/Advanced Science and Technology Education Center, Inc. & ASTEC CHARTER HS & ASTEC CHARTER HS",
            "stateProv": "Oklahoma",
            "nameShort": "Mortal ComBot",
            "country": "USA",
            "districtCode": null,
            "rookieYear": 2009,
            "robotName": "BoBo",
            "teamNumber": 2986
        },
        {
            "website": null,
            "city": "Farmington",
            "nameFull": "Twin Cities Business / UTC Aerospace Systems / General Dynamics / R&S Protection Services / Goodrich & FARMINGTON HIGH SCHOOL",
            "stateProv": "Minnesota",
            "nameShort": "Tigers",
            "country": "USA",
            "districtCode": null,
            "rookieYear": 2009,
            "robotName": null,
            "teamNumber": 2987
        },
        {
            "website": null,
            "city": "Berryville",
            "nameFull": "Heidi & Robert Hirsh / REC & CLARKE COUNTY HIGH",
            "stateProv": "Virginia",
            "nameShort": "RoboGenesis",
            "country": "USA",
            "districtCode": null,
            "rookieYear": 2009,
            "robotName": null,
            "teamNumber": 2988
        },
        {
            "website": null,
            "city": "Richfield",
            "nameFull": "Best Buy & ACADEMY OF HOLY ANGELS",
            "stateProv": "Minnesota",
            "nameShort": "Star Tech",
            "country": "USA",
            "districtCode": null,
            "rookieYear": 2009,
            "robotName": null,
            "teamNumber": 2989
        },
        {
            "website": null,
            "city": "Aumsville",
            "nameFull": "The Boeing Company/Freres Lumber/Zephyr Engineering/Meggitt Polymere Solutions/Elkins Ironworks/SCTC & Hotwire Robotics",
            "stateProv": "Oregon",
            "nameShort": "Hotwire",
            "country": "USA",
            "districtCode": "PNW",
            "rookieYear": 2009,
            "robotName": null,
            "teamNumber": 2990
        },
        {
            "website": null,
            "city": "Mandeville",
            "nameFull": "St. Tammany Parish School Board/National Defense Education Program/Chevron/Lockheed Martin/Fort Knox Climate Controlled Self Storage & MANDEVILLE HIGH SCHOOL",
            "stateProv": "Louisiana",
            "nameShort": "The SS Prometheus",
            "country": "USA",
            "districtCode": null,
            "rookieYear": 2009,
            "robotName": null,
            "teamNumber": 2992
        },
        {
            "website": null,
            "city": "North Logan",
            "nameFull": "Leidos / Ramada / Firehouse Pizzeria / Nucor Steel Utah & INTECH COLLEGIATE HIGH SCHOOL",
            "stateProv": "Utah",
            "nameShort": "InTech MegaBots",
            "country": "USA",
            "districtCode": null,
            "rookieYear": 2009,
            "robotName": null,
            "teamNumber": 2993
        },
        {
            "website": null,
            "city": "Kanata",
            "nameFull": "PROTOCASE / Lockheed Martin / Carleton University / Wesley Clover / Ottawa Catholic School Board & All Saints High School & Neighborhood Group",
            "stateProv": "Ontario",
            "nameShort": "ASTECHZ",
            "country": "Canada",
            "districtCode": null,
            "rookieYear": 2009,
            "robotName": "Atlas",
            "teamNumber": 2994
        },
        {
            "website": null,
            "city": "Colorado Springs",
            "nameFull": "Booz Allen Hamilton / Vertec Tool, Inc / Aeroflex / Challenger Learning Center / MCAD / BPO Elks Lodge 309 / Keysight Technologies / NDEP / Spectranetics / South COS Nissan / Heating & Plumbing Engineers, Inc. / Northrop Grumman / Hardware Specialty Co, Inc & CORONADO HIGH SCHOOL",
            "stateProv": "Colorado",
            "nameShort": "Cougars Gone Wired",
            "country": "USA",
            "districtCode": null,
            "rookieYear": 2009,
            "robotName": "Gunther",
            "teamNumber": 2996
        },
        {
            "website": null,
            "city": "Richmond",
            "nameFull": "Capital One/Genworth Foundation & THOMAS JEFFERSON HIGH",
            "stateProv": "Virginia",
            "nameShort": "VikingBots",
            "country": "USA",
            "districtCode": null,
            "rookieYear": 2009,
            "robotName": "B.O.T.",
            "teamNumber": 2998
        },
        {
            "website": null,
            "city": "Louisville",
            "nameFull": "Ford & JEFFERSONTOWN HIGH SCHOOL",
            "stateProv": "Kentucky",
            "nameShort": "Jeffersontown Robochargers",
            "country": "USA",
            "districtCode": null,
            "rookieYear": 2009,
            "robotName": null,
            "teamNumber": 3000
        },
        {
            "website": null,
            "city": "Canandaigua",
            "nameFull": "Xerox Corporation / WesLor Enterprises / Bradford White Water Heaters & CANANDAIGUA ACADEMY & MIDDLE SCHOOL",
            "stateProv": "New York",
            "nameShort": "TAN(X)",
            "country": "USA",
            "districtCode": null,
            "rookieYear": 2009,
            "robotName": null,
            "teamNumber": 3003
        },
        {
            "website": null,
            "city": "Dallas",
            "nameFull": "Texas Instruments/Vickery Meadows Foundation/Texas Workforce Commission & EMMETT J CONRAD H S",
            "stateProv": "Texas",
            "nameShort": " ROBOCHARGERS",
            "country": "USA",
            "districtCode": null,
            "rookieYear": 2009,
            "robotName": "LT Bolt",
            "teamNumber": 3005
        },
        {
            "website": null,
            "city": "Salt Lake City",
            "nameFull": "Rio Tinto / STEM Action Center / TSLOTS Futura Industries / University of Utah Physics Department / FIRST Hardship Grant / SolidWorks & WEST HIGH",
            "stateProv": "Utah",
            "nameShort": "Red Rock Robotics",
            "country": "USA",
            "districtCode": null,
            "rookieYear": 2009,
            "robotName": null,
            "teamNumber": 3006
        },
        {
            "website": null,
            "city": "Oakdale",
            "nameFull": "The Pentair Foundation / Diamond Machine / 3M Company / Cummins Power Generation / WSB & Associates / FOTH & TARTAN SENIOR HIGH",
            "stateProv": "Minnesota",
            "nameShort": "Robotitans",
            "country": "USA",
            "districtCode": null,
            "rookieYear": 2009,
            "robotName": null,
            "teamNumber": 3007
        },
        {
            "website": null,
            "city": "Honolulu",
            "nameFull": "BristleBots / PTC / FedEx / Friends of Robotics Organization Committee / BAE Systems & KALANI HIGH SCHOOL",
            "stateProv": "Hawaii",
            "nameShort": "Falcons",
            "country": "USA",
            "districtCode": null,
            "rookieYear": 2009,
            "robotName": "Crimson Typhoon",
            "teamNumber": 3008
        },
        {
            "website": null,
            "city": "Boulder City",
            "nameFull": "Draney Family/San Diego Gas & Electric/Copper Mountain Solar/Boulder City Sunrise Rotary/Goodfellow Corp./Harkins Family/Begley Family/Taylor Manning Family/Myra and James Davis/Boulder Dam Credit Union/ITT Technical Institute/Barth Electronics, Inc/Richner Air Conditioning/Fisher Space Pen/Boulder City Rotary/Desert Sun Reality/Alan Bowman/Richner Family/Boulder City Chamber of Commerce & BOULDER CITY HIGH SCHOOL",
            "stateProv": "Nevada",
            "nameShort": "High Scalers",
            "country": "USA",
            "districtCode": null,
            "rookieYear": 2009,
            "robotName": "Eagle one",
            "teamNumber": 3009
        },
        {
            "website": null,
            "city": "Centerburg ",
            "nameFull": "Ariel Corporation/AEP Ohio/JPMorganChase Foundation Volunteer Recognition Program/Community Foundation of Mount Vernon & Knox County & CENTERBURG HIGH SCHOOL",
            "stateProv": "Ohio",
            "nameShort": "The Red Plague",
            "country": "USA",
            "districtCode": null,
            "rookieYear": 2009,
            "robotName": "Grabriella",
            "teamNumber": 3010
        },
        {
            "website": null,
            "city": "Wiesbaden (US School)",
            "nameFull": "Wiesbaden Community Spouses Club / Armed Forces Communications and Electronics Association / BAE Systems / Leidos / Society of American Military Engineers / United States Air Force / Veterans of Foreign Wars Post 27 / Igus Inc. / Ruland Manufacturing / PTC / Air Force Association / US Army Corp of Engineers / Department of Defense Education Activity & Wiesbaden High School",
            "stateProv": "Hessen",
            "nameShort": "RoboWarriors",
            "country": "Germany",
            "districtCode": null,
            "rookieYear": 2009,
            "robotName": "Frau. POW! 7.0",
            "teamNumber": 3011
        },
        {
            "website": null,
            "city": "Vallejo ",
            "nameFull": "NASA/Google/NOVA Group/Bulldog Machine/Moschetti Coffee/XKT Engineering/Solano County Office of Education/Skyview Memorial/Vallejo City Unified School District/Minuteman Press of Vallejo/Klimisch, Inc. Collision Repair Specialists & VALLEJO HIGH",
            "stateProv": "California",
            "nameShort": "Zombots",
            "country": "USA",
            "districtCode": null,
            "rookieYear": 2009,
            "robotName": null,
            "teamNumber": 3013
        },
        {
            "website": null,
            "city": "Spencerport",
            "nameFull": "Xerox Corporation/Exelis/Baxter/UTC/Advantage Federal Credit Union/Flower City Communications/ANKOM & SPENCERPORT HIGH SCHOOL",
            "stateProv": "New York",
            "nameShort": "Ranger Robotics",
            "country": "USA",
            "districtCode": null,
            "rookieYear": 2009,
            "robotName": "Ms. Marlene",
            "teamNumber": 3015
        },
        {
            "website": null,
            "city": "Houston",
            "nameFull": "Texas Workforce Commision & Cypress Creek High School",
            "stateProv": "Texas",
            "nameShort": "T.E.S.L.A. Robotics",
            "country": "USA",
            "districtCode": null,
            "rookieYear": 2009,
            "robotName": "Kirby-Bot",
            "teamNumber": 3016
        },
        {
            "website": null,
            "city": "Saint Peter",
            "nameFull": "Medtronic/Neighborhood Group/Gustavus Adolphus College/Analog Devices Inc./DLC, Inc",
            "stateProv": "Minnesota",
            "nameShort": "Nordic Storm",
            "country": "USA",
            "districtCode": null,
            "rookieYear": 2009,
            "robotName": null,
            "teamNumber": 3018
        },
        {
            "website": null,
            "city": "Scottsdale",
            "nameFull": "Employees of Microchip Technology / The Boeing Company / Gobucks Inc. & CHAPARRAL HIGH SCHOOL",
            "stateProv": "Arizona",
            "nameShort": "Firebirds",
            "country": "USA",
            "districtCode": null,
            "rookieYear": 2009,
            "robotName": "Carcinus",
            "teamNumber": 3019
        },
        {
            "website": null,
            "city": "Escondido",
            "nameFull": "ViaSat / Nordson Asymtek / BAE Systems & CLASSICAL ACADEMY HIGH",
            "stateProv": "California",
            "nameShort": "The  Agency",
            "country": "USA",
            "districtCode": null,
            "rookieYear": 2009,
            "robotName": null,
            "teamNumber": 3021
        },
        {
            "website": null,
            "city": "Elk River",
            "nameFull": "Medtronic & ELK RIVER SENIOR HIGH",
            "stateProv": "Minnesota",
            "nameShort": "STARK Industries",
            "country": "USA",
            "districtCode": null,
            "rookieYear": 2009,
            "robotName": "Jarvis",
            "teamNumber": 3023
        },
        {
            "website": null,
            "city": "Ashland",
            "nameFull": "Evogeneo / Alan and Priscilla Oppenheimer Foundation / Ashland Home Net / Oregon Department of Education / Modern Fan Co. & ASHLAND HIGH SCHOOL",
            "stateProv": "Oregon",
            "nameShort": "My Favorite Team",
            "country": "USA",
            "districtCode": "PNW",
            "rookieYear": 2009,
            "robotName": null,
            "teamNumber": 3024
        },
        {
            "website": null,
            "city": "Delano",
            "nameFull": "Sil-Pro & DELANO SENIOR HIGH",
            "stateProv": "Minnesota",
            "nameShort": "Orange Crush",
            "country": "USA",
            "districtCode": null,
            "rookieYear": 2009,
            "robotName": "na",
            "teamNumber": 3026
        },
        {
            "website": null,
            "city": "Ventura",
            "nameFull": "Amgen/JMP Racing/Oxnard Precision Fabrication/McConnell's Fine Ice Cream and Yogurt/Intel & ST BONAVENTURE HIGH SCHOOL",
            "stateProv": "California",
            "nameShort": "Seraphim Systems",
            "country": "USA",
            "districtCode": null,
            "rookieYear": 2009,
            "robotName": null,
            "teamNumber": 3027
        },
        {
            "website": null,
            "city": "Hidalgo",
            "nameFull": "American Electric Power/South Texas College Technology Campus/FIRST in Texas & HIDALGO H S",
            "stateProv": "Texas",
            "nameShort": "Robot Commando Squad",
            "country": "USA",
            "districtCode": null,
            "rookieYear": 2009,
            "robotName": null,
            "teamNumber": 3028
        },
        {
            "website": null,
            "city": "Pharr",
            "nameFull": "PSJA ISD/American Electric Power/Texas Workforce Commission & FIRST in Texas & T-STEM EARLY COLLEGE H S",
            "stateProv": "Texas",
            "nameShort": "T-STEM Titans",
            "country": "USA",
            "districtCode": null,
            "rookieYear": 2009,
            "robotName": null,
            "teamNumber": 3029
        },
        {
            "website": null,
            "city": "Kefar Blum",
            "nameFull": "Netafim/PTC & Emek Hula",
            "stateProv": "HaZafon (Northern)",
            "nameShort": "Galileo",
            "country": "Israel",
            "districtCode": null,
            "rookieYear": 2009,
            "robotName": "Galileo",
            "teamNumber": 3034
        },
        {
            "website": null,
            "city": "Corpus Christi",
            "nameFull": "Texas Workforce Commission/FIRST in Texas/Time Warner & COLLEGIATE H S",
            "stateProv": "Texas",
            "nameShort": "Droid Rage",
            "country": "USA",
            "districtCode": null,
            "rookieYear": 2009,
            "robotName": "Dr. Droid",
            "teamNumber": 3035
        },
        {
            "website": null,
            "city": "Deer River",
            "nameFull": "Blandin Foundation & DEER RIVER SECONDARY",
            "stateProv": "Minnesota",
            "nameShort": "DROBA Warriors",
            "country": "USA",
            "districtCode": null,
            "rookieYear": 2009,
            "robotName": null,
            "teamNumber": 3036
        },
        {
            "website": null,
            "city": "Longview",
            "nameFull": "Texas Workforce Commission/Diagnostic Clinic of Longview/Westlake Chemicals/Eastman Chemicals & LONGVIEW H S",
            "stateProv": "Texas",
            "nameShort": "GLOBOTS",
            "country": "USA",
            "districtCode": null,
            "rookieYear": 2009,
            "robotName": "Globot",
            "teamNumber": 3037
        },
        {
            "website": null,
            "city": "North Branch",
            "nameFull": "St. Jude Medical Foundation & CHISAGO LAKES SENIOR HIGH & NORTH BRANCH SENIOR HIGH",
            "stateProv": "Minnesota",
            "nameShort": "ICE",
            "country": "USA",
            "districtCode": null,
            "rookieYear": 2009,
            "robotName": "ICE",
            "teamNumber": 3038
        },
        {
            "website": null,
            "city": "Destrehan",
            "nameFull": "ADS Systems, LLC/St. Charles Parish Public Schools/Motiva/Cospolich/Anthony's Ace Hardware/Aerotyme/Shirt Shack/Engine Monitor & DESTREHAN HIGH SCHOOL",
            "stateProv": "Louisiana",
            "nameShort": "Wildcat Robotics",
            "country": "USA",
            "districtCode": null,
            "rookieYear": 2009,
            "robotName": "\"The Pistol\"",
            "teamNumber": 3039
        },
        {
            "website": null,
            "city": "Apple Valley",
            "nameFull": "Mpls St. Paul Magazine/TE Connectivity Foundation /Thomson Reuters/Power Systems Research/RBA/Lockheed Martin & EASTVIEW SENIOR HIGH",
            "stateProv": "Minnesota",
            "nameShort": "Cobalt Catalysts",
            "country": "USA",
            "districtCode": null,
            "rookieYear": 2009,
            "robotName": "ELI",
            "teamNumber": 3042
        },
        {
            "website": null,
            "city": "El Paso",
            "nameFull": "DaVinci Robotics & DAVINCI SCHOOL FOR SCIENCE AND THE ARTS",
            "stateProv": "Texas",
            "nameShort": "Dragons",
            "country": "USA",
            "districtCode": null,
            "rookieYear": 2009,
            "robotName": "Virgilio",
            "teamNumber": 3043
        },
        {
            "website": null,
            "city": "Ballston Spa",
            "nameFull": "Ballston Spa National Bank / Town of Malta GLOBAL FOUNDRIES Community Foundation / General Electric / Malta Business & Professional Association / Mangino Buick GMC / Logo Wearhaus / TCT Federal Credit Union / Technical Building Services / CSArch / Guyson Corporation / Adirondack Trust Company / The Bell Family / Hound Dog Graphics / Specialty Silicone Products / Bechtel & BALLSTON SPA SENIOR HIGH SCHOOL",
            "stateProv": "New York",
            "nameShort": "Team 0xBE4",
            "country": "USA",
            "districtCode": null,
            "rookieYear": 2009,
            "robotName": null,
            "teamNumber": 3044
        },
        {
            "website": null,
            "city": "San Mateo",
            "nameFull": "JUNIPERO SERRA HIGH SCHOOL",
            "stateProv": "California",
            "nameShort": "SWAT Robotics",
            "country": "USA",
            "districtCode": null,
            "rookieYear": 2009,
            "robotName": null,
            "teamNumber": 3045
        },
        {
            "website": null,
            "city": "Mesa ",
            "nameFull": "East Valley Institute Of Technology #401 & East Valley Institute of Technology",
            "stateProv": "Arizona",
            "nameShort": "Critical Mass",
            "country": "USA",
            "districtCode": null,
            "rookieYear": 2009,
            "robotName": "Cobalt",
            "teamNumber": 3048
        },
        {
            "website": null,
            "city": "Bremerton",
            "nameFull": "Puget Sound Naval Shipyard/National Defense Education Program & BREMERTON HIGH SCHOOL",
            "stateProv": "Washington",
            "nameShort": "BremerTron",
            "country": "USA",
            "districtCode": "PNW",
            "rookieYear": 2009,
            "robotName": null,
            "teamNumber": 3049
        },
        {
            "website": null,
            "city": "Queens Village",
            "nameFull": "Pershing Square & MARTIN VAN BUREN HIGH SCHOOL",
            "stateProv": "New York",
            "nameShort": "VB Stingers",
            "country": "USA",
            "districtCode": null,
            "rookieYear": 2009,
            "robotName": "King Kang",
            "teamNumber": 3053
        },
        {
            "website": null,
            "city": "Grand Marais",
            "nameFull": "Arrowhead Electric/Medtronic & COOK COUNTY SENIOR HIGH",
            "stateProv": "Minnesota",
            "nameShort": "IceStorm",
            "country": "USA",
            "districtCode": null,
            "rookieYear": 2009,
            "robotName": "Cedric",
            "teamNumber": 3054
        },
        {
            "website": null,
            "city": "Austin",
            "nameFull": "Hormel Foundation/Medtronic & AUSTIN SENIOR HIGH",
            "stateProv": "Minnesota",
            "nameShort": "Furious George",
            "country": "USA",
            "districtCode": null,
            "rookieYear": 2009,
            "robotName": "George",
            "teamNumber": 3055
        },
        {
            "website": null,
            "city": "Annandale",
            "nameFull": "Dura Supreme / Malco Tools / Country Chevrolet / Annandale State Bank / Annandale Lions / Zahler Photography & ANNANDALE SENIOR HIGH",
            "stateProv": "Minnesota",
            "nameShort": "AnnDroids",
            "country": "USA",
            "districtCode": null,
            "rookieYear": 2009,
            "robotName": "Noisy Boy",
            "teamNumber": 3058
        },
        {
            "website": null,
            "city": "Yonkers",
            "nameFull": "Con Edison/Economos Foundation/NCC: Gateway Academy & RIVERSIDE HIGH SCHOOL",
            "stateProv": "New York",
            "nameShort": "Riverside Envirobotics",
            "country": "USA",
            "districtCode": null,
            "rookieYear": 2009,
            "robotName": null,
            "teamNumber": 3059
        },
        {
            "website": null,
            "city": "Naperville",
            "nameFull": "Navistar / Grid Connect / Molex / Create Cut Invent / Motorola Solutions Foundation / Exelon  / Midwest Printed Circuit Services, Inc. / Lextech & NAPERVILLE NORTH HIGH SCHOOL",
            "stateProv": "Illinois",
            "nameShort": "Huskie Robotics",
            "country": "USA",
            "districtCode": null,
            "rookieYear": 2009,
            "robotName": "Bonnie",
            "teamNumber": 3061
        },
        {
            "website": null,
            "city": "Natrona Heights",
            "nameFull": "St. Joseph High School",
            "stateProv": "Pennsylvania",
            "nameShort": "Spartan Robotics",
            "country": "USA",
            "districtCode": null,
            "rookieYear": 2009,
            "robotName": "Marie Curie",
            "teamNumber": 3062
        },
        {
            "website": null,
            "city": "Jatt",
            "nameFull": "SRT/frenkel & jatt",
            "stateProv": "HaMerkaz (Central)",
            "nameShort": "Jatt High School",
            "country": "Israel",
            "districtCode": null,
            "rookieYear": 2009,
            "robotName": "jatt",
            "teamNumber": 3065
        },
        {
            "website": null,
            "city": "Geneva",
            "nameFull": "The Label Printers / MayTech / Geneva Ale House & GENEVA COMMUNITY HIGH SCHOOL",
            "stateProv": "Illinois",
            "nameShort": "Robovikes",
            "country": "USA",
            "districtCode": null,
            "rookieYear": 2009,
            "robotName": null,
            "teamNumber": 3067
        },
        {
            "website": null,
            "city": "Shoreline",
            "nameFull": "team pronto parents/metors/The Boeing Company/Microsoft/shoreline foundation/University of Washington & SHOREWOOD HIGH SCHOOL",
            "stateProv": "Washington",
            "nameShort": "Team Pronto",
            "country": "USA",
            "districtCode": "PNW",
            "rookieYear": 2009,
            "robotName": "Marie Antointote ",
            "teamNumber": 3070
        },
        {
            "website": null,
            "city": "Wytheville",
            "nameFull": "Verizon / Nordson-Xaloy & WYTHE COUNTY TECH CENTER",
            "stateProv": "Virginia",
            "nameShort": "Backwoods Bots",
            "country": "USA",
            "districtCode": null,
            "rookieYear": 2009,
            "robotName": " LEEEROOY!!!",
            "teamNumber": 3072
        },
        {
            "website": null,
            "city": "Hod-Ha'Sharon",
            "nameFull": "Hod Hasharon Municipality / Qualcomm Incorporated / Bnai Brith Hod Hasharon / CONTROP PRECISION TECHNOLOGIES LTD / Zitec technology / Keter Plastic Ltd. / Beiman-Cohen-Biran Ltd. / Yahal Zilka / Peled Ben-Ami Ltd. / Pikok Computes / MILPER / Robomow & Hadarim",
            "stateProv": "HaMerkaz (Central)",
            "nameShort": "Ha-Dream Team",
            "country": "Israel",
            "districtCode": null,
            "rookieYear": 2009,
            "robotName": null,
            "teamNumber": 3075
        },
        {
            "website": null,
            "city": "Bloomington",
            "nameFull": "Microsoft / Thermo King / Clariant International / Dalsin Industries / Memphis Grills / Wair Products / Bloomington Heritage Days / Education Foundation of Bloomington / Peterson Family / Hart Family / Lindemann Family / Rauenhorst Family / Sjostrand Family & KENNEDY SENIOR HIGH",
            "stateProv": "Minnesota",
            "nameShort": "RoboEagles",
            "country": "USA",
            "districtCode": null,
            "rookieYear": 2009,
            "robotName": "Fritz 5",
            "teamNumber": 3081
        },
        {
            "website": null,
            "city": "Minnetonka",
            "nameFull": "St. Jude Medical, Inc / Rockwell Automation / Integrity Global Solutions, LLC. & MINNETONKA SENIOR HIGH",
            "stateProv": "Minnesota",
            "nameShort": "Chicken Bot Pie",
            "country": "USA",
            "districtCode": null,
            "rookieYear": 2009,
            "robotName": "Robot Chicken",
            "teamNumber": 3082
        },
        {
            "website": null,
            "city": "Maagan Michael",
            "nameFull": "Caeser Stone / Gold-Bar / PTC / Plasson / Alubin / Kibbutz Sdot Yam & HOME SCHOOL",
            "stateProv": "HaZafon (Northern)",
            "nameShort": "Artemis",
            "country": "Israel",
            "districtCode": null,
            "rookieYear": 2009,
            "robotName": "Menni",
            "teamNumber": 3083
        },
        {
            "website": null,
            "city": "Winona",
            "nameFull": "Boston Scientific Company/Miller Ingenuity/Wincraft/Peerless Chain/RTP Company/Benchmark Electronics/Concept Tool/Excel Images/Miller Scrap/MN SE Technical College/jcpenney/Medtronic/SRT & WINONA SENIOR HIGH",
            "stateProv": "Minnesota",
            "nameShort": "Winhawks",
            "country": "USA",
            "districtCode": null,
            "rookieYear": 2009,
            "robotName": "Jeff",
            "teamNumber": 3090
        }
    ]
}